truliooapiclient
